libtorrent.so
lbry_libtorrent-1.2.4.dist-info/DESCRIPTION.rst
lbry_libtorrent-1.2.4.dist-info/METADATA
lbry_libtorrent-1.2.4.dist-info/RECORD
lbry_libtorrent-1.2.4.dist-info/WHEEL
lbry_libtorrent-1.2.4.dist-info/metadata.json
lbry_libtorrent-1.2.4.dist-info/top_level.txt
